cakephp_theme/__init__.py
cakephp_theme/footer.html
cakephp_theme/globaltoc.html
cakephp_theme/layout.html
cakephp_theme/localtoc.html
cakephp_theme/relbar1.html
cakephp_theme/search.html
cakephp_theme/theme.conf
cakephp_theme/versions.html
cakephp_theme/__pycache__/__init__.cpython-37.pyc
cakephp_theme/menu/documentation.html
cakephp_theme/menu/footer-documentation.html
cakephp_theme/menu/help.html
cakephp_theme/static/Baked-For-CakePHP.png
cakephp_theme/static/app.js
cakephp_theme/static/cake-logo.png
cakephp_theme/static/favicon.ico
cakephp_theme/static/favicon.png
cakephp_theme/static/logo-cake.png
cakephp_theme/static/open-hub.png
cakephp_theme/static/opensearchdescription-book-3-x.xml
cakephp_theme/static/pdf-logo.png
cakephp_theme/static/rackspace.png
cakephp_theme/static/search.png
cakephp_theme/static/css/app.css
cakephp_theme/static/css/bootstrap.min.css
cakephp_theme/static/css/default.css
cakephp_theme/static/css/font-awesome.min.css
cakephp_theme/static/css/fonts.css
cakephp_theme/static/css/pygments.css
cakephp_theme/static/css/responsive.css
cakephp_theme/static/css/rtd.css
cakephp_theme/static/css/style.css
cakephp_theme/static/font/FontAwesome.otf
cakephp_theme/static/font/cakedingbats-webfont.eot
cakephp_theme/static/font/cakedingbats-webfont.svg
cakephp_theme/static/font/cakedingbats-webfont.ttf
cakephp_theme/static/font/cakedingbats-webfont.woff
cakephp_theme/static/font/cakedingbats-webfont.woff2
cakephp_theme/static/font/fontawesome-webfont.eot
cakephp_theme/static/font/fontawesome-webfont.svg
cakephp_theme/static/font/fontawesome-webfont.ttf
cakephp_theme/static/font/fontawesome-webfont.woff
cakephp_theme/static/font/fontawesome-webfont.woff2
cakephp_theme/static/font/glyphicons-halflings-regular.eot
cakephp_theme/static/font/glyphicons-halflings-regular.svg
cakephp_theme/static/font/glyphicons-halflings-regular.ttf
cakephp_theme/static/font/glyphicons-halflings-regular.woff
cakephp_theme/static/font/glyphicons-halflings-regular.woff2
cakephp_theme-1.1.3.dist-info/LICENSE
cakephp_theme-1.1.3.dist-info/METADATA
cakephp_theme-1.1.3.dist-info/WHEEL
cakephp_theme-1.1.3.dist-info/top_level.txt
cakephp_theme-1.1.3.dist-info/RECORD
