Metadata-Version: 2.1
Name: cakephp-theme
Version: 1.1.3
Summary: A Sphinx theme for CakePHP doc sites
Home-page: https://github.com/cakephp/doc-theme
Author: Cake Software Foundation, Inc.
Author-email: hi@cakephp.com
License: UNKNOWN
Platform: UNKNOWN
Classifier: Intended Audience :: Developers
Classifier: Operating System :: OS Independent
Classifier: Topic :: Documentation
Classifier: Topic :: Software Development :: Documentation
Classifier: Programming Language :: Python
Classifier: Programming Language :: Python :: 2.6
Classifier: Programming Language :: Python :: 2.7
Classifier: Programming Language :: Python :: 3.2
Classifier: Programming Language :: Python :: 3.3
Classifier: Programming Language :: Python :: 3.4
